load_market_data-0.3.6.dist-info/METADATA
load_market_data-0.3.6.dist-info/WHEEL
load_market_data/__init__.py
load_market_data/__init__.pyi
load_market_data/py.typed
load_market_data/load_market_data.cpython-312-x86_64-linux-gnu.so
load_market_data-0.3.6.dist-info/RECORD
