Metadata-Version: 2.4
Name: load_market_data
Version: 0.3.6
Requires-Dist: maturin>=1.8.1
Requires-Dist: patchelf>=0.17.2.1 ; sys_platform == 'linux'
Summary: Add your description here
Requires-Python: >=3.12
